fenic-0.7.0.dist-info/METADATA
fenic-0.7.0.dist-info/WHEEL
fenic-0.7.0.dist-info/entry_points.txt
fenic-0.7.0.dist-info/licenses/LICENSE
fenic/__init__.py
fenic/_backends/cloud/__init__.py
fenic/_backends/cloud/catalog.py
fenic/_backends/cloud/cloud_catalog_utils.py
fenic/_backends/cloud/engine_config.py
fenic/_backends/cloud/execution.py
fenic/_backends/cloud/manager.py
fenic/_backends/cloud/metrics.py
fenic/_backends/cloud/session_state.py
fenic/_backends/cloud/settings.py
fenic/_backends/local/__init__.py
fenic/_backends/local/async_udf_stream.py
fenic/_backends/local/async_utils.py
fenic/_backends/local/catalog.py
fenic/_backends/local/execution.py
fenic/_backends/local/lineage.py
fenic/_backends/local/manager.py
fenic/_backends/local/model_registry.py
fenic/_backends/local/physical_plan/__init__.py
fenic/_backends/local/physical_plan/aggregate.py
fenic/_backends/local/physical_plan/base.py
fenic/_backends/local/physical_plan/join.py
fenic/_backends/local/physical_plan/optimizer/__init__.py
fenic/_backends/local/physical_plan/optimizer/base.py
fenic/_backends/local/physical_plan/optimizer/merge_duckdb_nodes.py
fenic/_backends/local/physical_plan/sink.py
fenic/_backends/local/physical_plan/source.py
fenic/_backends/local/physical_plan/transform.py
fenic/_backends/local/physical_plan/utils.py
fenic/_backends/local/polars_plugins/__init__.py
fenic/_backends/local/polars_plugins/chunking.py
fenic/_backends/local/polars_plugins/dtypes.py
fenic/_backends/local/polars_plugins/fuzz.py
fenic/_backends/local/polars_plugins/jinja.py
fenic/_backends/local/polars_plugins/json.py
fenic/_backends/local/polars_plugins/markdown.py
fenic/_backends/local/polars_plugins/regex.py
fenic/_backends/local/polars_plugins/tokenization.py
fenic/_backends/local/polars_plugins/transcripts.py
fenic/_backends/local/semantic_operators/__init__.py
fenic/_backends/local/semantic_operators/analyze_sentiment.py
fenic/_backends/local/semantic_operators/base.py
fenic/_backends/local/semantic_operators/classify.py
fenic/_backends/local/semantic_operators/cluster.py
fenic/_backends/local/semantic_operators/extract.py
fenic-0.7.0.dist-info/RECORD
